CHANGES.txt
LICENSE.txt
MANIFEST.in
README.txt
setup.py
django_smartdbstorage.egg-info/PKG-INFO
django_smartdbstorage.egg-info/SOURCES.txt
django_smartdbstorage.egg-info/dependency_links.txt
django_smartdbstorage.egg-info/requires.txt
django_smartdbstorage.egg-info/top_level.txt
smartdbstorage/__init__.py
smartdbstorage/admin.py
smartdbstorage/file.py
smartdbstorage/models.py
smartdbstorage/storage.py
smartdbstorage/urls.py
smartdbstorage/views.py
smartdbstorage/migrations/0001_initial.py
smartdbstorage/migrations/0002_auto__add_dbpool__del_field_dbfile_prefix__add_field_dbfile_pool__del_.py
smartdbstorage/migrations/__init__.py