Metadata-Version: 1.0
Name: django-smartdbstorage
Version: 0.1.1
Summary: A Django Model based file storage.
Home-page: http://dperetti.github.com/Django-SmartDBStorage
Author: Dominique PERETTI
Author-email: dperetti@lachoseinteractive.net
License: LICENSE.txt
Platform: UNKNOWN
